PDFs/put_your_pdf_here.txt
Unlocked_PDFs/unlocked_pdf_here.txt
upppdf/__init__.py
upppdf/pdf_unlocker.py
upppdf/version.py
upppdf-1.0.8.dist-info/licenses/LICENSE
upppdf-1.0.8.dist-info/METADATA
upppdf-1.0.8.dist-info/WHEEL
upppdf-1.0.8.dist-info/entry_points.txt
upppdf-1.0.8.dist-info/top_level.txt
upppdf-1.0.8.dist-info/RECORD
