Metadata-Version: 2.4
Name: upppdf
Version: 1.0.8
Summary: Unlock password protected PDF files using multiple methods
Home-page: https://github.com/abozaralizadeh/UPPPDF
Author: Abozar Alizadeh
Author-email: Abozar Alizadeh <abozar.alizadeh@gmail.com>
License: MIT
Project-URL: Homepage, https://github.com/abozaralizadeh/UPPPDF
Project-URL: Repository, https://github.com/abozaralizadeh/UPPPDF
Project-URL: Issues, https://github.com/abozaralizadeh/UPPPDF/issues
Project-URL: Documentation, https://github.com/abozaralizadeh/UPPPDF#readme
Keywords: pdf,unlock,password,decrypt,security
Classifier: Development Status :: 4 - Beta
Classifier: Intended Audience :: End Users/Desktop
Classifier: License :: OSI Approved :: MIT License
Classifier: Operating System :: OS Independent
Classifier: Programming Language :: Python :: 3
Classifier: Programming Language :: Python :: 3.8
Classifier: Programming Language :: Python :: 3.9
Classifier: Programming Language :: Python :: 3.10
Classifier: Programming Language :: Python :: 3.11
Classifier: Programming Language :: Python :: 3.12
Classifier: Programming Language :: Python :: 3.13
Classifier: Topic :: Office/Business
Classifier: Topic :: Utilities
Requires-Python: >=3.8
License-File: LICENSE
Requires-Dist: PyPDF2>=3.0.0
Requires-Dist: pikepdf>=9.0.0
Requires-Dist: pymupdf>=1.24.0
Dynamic: author
Dynamic: home-page
Dynamic: license-file
Dynamic: requires-python
